YunJisuanjishuYuYingyongXuexiJiaochengCYuyanBianchengWangFix1/README.md
YunJisuanjishuYuYingyongXuexiJiaochengCYuyanBianchengWangFix1/__init__.py
YunJisuanjishuYuYingyongXuexiJiaochengCYuyanBianchengWangFix1/__main__.py
YunJisuanjishuYuYingyongXuexiJiaochengCYuyanBianchengWangFix1/file.epub
YunJisuanjishuYuYingyongXuexiJiaochengCYuyanBianchengWangFix1/index.html
YunJisuanjishuYuYingyongXuexiJiaochengCYuyanBianchengWangFix1/css/__init__.py
YunJisuanjishuYuYingyongXuexiJiaochengCYuyanBianchengWangFix1/css/annotations.css
YunJisuanjishuYuYingyongXuexiJiaochengCYuyanBianchengWangFix1/css/main.css
YunJisuanjishuYuYingyongXuexiJiaochengCYuyanBianchengWangFix1/css/normalize.css
YunJisuanjishuYuYingyongXuexiJiaochengCYuyanBianchengWangFix1/css/popup.css
YunJisuanjishuYuYingyongXuexiJiaochengCYuyanBianchengWangFix1/font/__init__.py
YunJisuanjishuYuYingyongXuexiJiaochengCYuyanBianchengWangFix1/font/fontello.eot
YunJisuanjishuYuYingyongXuexiJiaochengCYuyanBianchengWangFix1/font/fontello.svg
YunJisuanjishuYuYingyongXuexiJiaochengCYuyanBianchengWangFix1/font/fontello.ttf
YunJisuanjishuYuYingyongXuexiJiaochengCYuyanBianchengWangFix1/font/fontello.woff
YunJisuanjishuYuYingyongXuexiJiaochengCYuyanBianchengWangFix1/img/__init__.py
YunJisuanjishuYuYingyongXuexiJiaochengCYuyanBianchengWangFix1/img/annotator-glyph-sprite.png
YunJisuanjishuYuYingyongXuexiJiaochengCYuyanBianchengWangFix1/img/annotator-icon-sprite.png
YunJisuanjishuYuYingyongXuexiJiaochengCYuyanBianchengWangFix1/img/apple-touch-icon.png
YunJisuanjishuYuYingyongXuexiJiaochengCYuyanBianchengWangFix1/img/cancelfullscreen.png
YunJisuanjishuYuYingyongXuexiJiaochengCYuyanBianchengWangFix1/img/close.png
YunJisuanjishuYuYingyongXuexiJiaochengCYuyanBianchengWangFix1/img/fullscreen.png
YunJisuanjishuYuYingyongXuexiJiaochengCYuyanBianchengWangFix1/img/loader.gif
YunJisuanjishuYuYingyongXuexiJiaochengCYuyanBianchengWangFix1/img/menu-icon.png
YunJisuanjishuYuYingyongXuexiJiaochengCYuyanBianchengWangFix1/img/save.png
yun_jisuanjishu_yu_yingyong_xuexi_jiaocheng_c_yuyan_biancheng_wang_fix1-2025.3.24.1.dist-info/METADATA
yun_jisuanjishu_yu_yingyong_xuexi_jiaocheng_c_yuyan_biancheng_wang_fix1-2025.3.24.1.dist-info/WHEEL
yun_jisuanjishu_yu_yingyong_xuexi_jiaocheng_c_yuyan_biancheng_wang_fix1-2025.3.24.1.dist-info/entry_points.txt
yun_jisuanjishu_yu_yingyong_xuexi_jiaocheng_c_yuyan_biancheng_wang_fix1-2025.3.24.1.dist-info/top_level.txt
yun_jisuanjishu_yu_yingyong_xuexi_jiaocheng_c_yuyan_biancheng_wang_fix1-2025.3.24.1.dist-info/RECORD
